Workbook

Sheet Read Me
B2: Cheerio Growth Guide — Unit Economics & Adoption Model
B3: Financial Projections, Token Economics, Infrastructure Sizing & Retention Impact
B5: Document Version | C5: 1.0 (Production Candidate)
B6: Author | C6: Cheerio AI Product Intern Candidate
B7: Scope | C7: 12-Month Rolling Projections for Cheerio Growth Guide (5,000 Starting Active Businesses)
B8: Currency | C8: Indian Rupee (INR - ₹) with USD conversion for API token rates
B9: Central Objective | C9: Model unit economics, AI token costs, infrastructure overhead, and retention-driven revenue.
B11: WORKBOOK NAVIGATION
B12: 1. Read Me | C12: Overview, model structure, methodology and usage instructions.
B13: 2. Assumptions | C13: Centralized, editable inputs for cohort sizing, conversion rates, AI pricing, and infrastructure.
B14: 3. Adoption Model | C14: 12-month adoption funnel: reach, engagement, feature activations, and meaningful use cohorts.
B15: 4. AI & Infra Cost | C15: Token consumption, OpenAI GPT-4o-mini API fees, cloud hosting, and cost per activation.
B16: 5. Revenue & Margin | C16: Expected-value retention revenue, net modeled benefit, and contribution margins.
B17: 6. Scenarios | C17: Conservative, Base, and Optimistic cases with multidimensional sensitivity matrices.
B18: 7. Monthly Audit | C18: Formula-driven reconciliation checks ensuring model consistency and preventing double-counting.
B19: 8. Sources | C19: Verified benchmark sources, official API pricing references, and model disclaimers.
B21: METHODOLOGY & GUARDRAILS
B22: Expected-Value Basis | C22: Retention revenue = Adopting Businesses × Hypothesized Retention Lift in pp × Monthly Plan ARPU.
B23: No Double-Counting | C23: Revenue is tied strictly to newly retained cohorts without compounding previously credited gains.
B24: Illustrative Nature | C24: All retention lifts (+2.0 pp baseline) represent testable hypotheses subject to 2-week baseline validation.
B25: Run-Rate Annualization | C25: Exit ARR (₹26,27,124) is compared against Annualized Month-12 Cost (₹14,21,016), yielding Exit Net Benefit ₹12,06,108 (45.9% margin), distinct from Year-1 in-period cash flow (+₹1,67,881 net, 11.4% margin).
B26: Hosting Cost Attribution | C26: Base model allocates full-platform cloud hosting (₹10,05,870) across all 67,058 account-months as a conservative stress test. Incremental feature-only allocation yields >80% margin. Platform hosting must not be double-counted against baseline WhatsApp campaign P&Ls.

Sheet Assumptions
B2: Model Assumptions & Central Input Parameters
B3: Cells highlighted in Light Blue represent editable baseline inputs. All other tabs dynamically reference this table.
B5: Parameter Name | C5: Value | D5: Unit | E5: Source & Notes
B6: 1. Business Baseline Cohort
B7: Starting Active Businesses | C7: 5000 | D7: Accounts | E7: Assignment specification baseline (Cheerio MAU)
B8: Monthly Organic Growth Rate | C8: 0.02 | D8: Percent | E8: Estimated net month-over-month account expansion
B9: Average Monthly Plan Revenue (ARPU) | C9: 2999 | D9: INR / mo | E9: Representative Growth Plan tier for D2C brands
B10: Baseline Monthly Churn Rate | C10: 0.05 | D10: Percent | E10: Current pre-intervention churn (95% retention)
B11: 2. Growth Guide Funnel & Conversion Rates
B12: Monthly Recommendation Reach % | C12: 0.7 | D12: Percent | E12: % of active businesses exposed to Growth Guide prompts
B13: Engagement Rate (% of Reached) | C13: 0.4 | D13: Percent | E13: % who click recommendation or complete assessment
B14: Feature Activation Rate (% of Engaged) | C14: 0.25 | D14: Percent | E14: % of engaged businesses who complete setup wizard
B15: Meaningful Use Qualification Rate | C15: 0.6 | D15: Percent | E15: % of activated accounts recording qualifying use within 30d
B16: Hypothesized Retention Lift for Adopters | C16: 0.02 | D16: pp (monthly) | E16: Hypothesized churn reduction for adopting businesses (+2.0 pp)
B17: 3. AI Model & Token Economics
B18: AI Model Name | C18: OpenAI GPT-4o-mini | D18: Text | E18: Verified cost-effective production model tier
B19: Input Token Price ($ / 1M tokens) | C19: 0.15 | D19: USD / 1M | E19: Official OpenAI Pricing schedule (developers.openai.com/api/docs/models/gpt-4o-mini)
B20: Output Token Price ($ / 1M tokens) | C20: 0.6 | D20: USD / 1M | E20: Official OpenAI Pricing schedule (developers.openai.com/api/docs/models/gpt-4o-mini)
B21: USD to INR Exchange Rate | C21: 84 | D21: INR / USD | E21: Editable illustrative conversion assumption (not a fixed currency peg)
B22: Avg Input Tokens per Interaction | C22: 650 | D22: Tokens | E22: Context, prompt instructions, FAQ templates
B23: Avg Output Tokens per Interaction | C23: 250 | D23: Tokens | E23: Generated recommendation/response payload
B24: Avg AI Interactions per Business / Mo | C24: 18 | D24: Calls / mo | E24: Simulated wizard setups, FAQ queries, automation tests
B25: 4. Platform Infrastructure Overhead
B26: Variable Cloud Cost per Active Account | C26: 15 | D26: INR / mo | E26: AWS/GCP database, webhook listeners, serverless execution
B27: Fixed Monthly Infrastructure Overhead | C27: 25000 | D27: INR / mo | E27: Dedicated staging clusters, monitoring, logging ledger

Sheet Adoption Model
B2: 12-Month Feature Adoption Funnel
B3: Models the progression of Cheerio active businesses through recommendation reach, engagement, activation, and meaningful use.
B5: Month | C5: Active Businesses | D5: Reached (70%) | E5: Engaged (40%) | F5: New Activated (25%) | G5: Cumulative Activated | H5: Meaningful Use (60%)
B6: Month 1 | C6: =Assumptions!$C$7 | D6: =ROUND(C6 * Assumptions!$C$12, 0) | E6: =ROUND(D6 * Assumptions!$C$13, 0) | F6: =ROUND(E6 * Assumptions!$C$14, 0) | G6: =F6 | H6: =ROUND(F6 * Assumptions!$C$15, 0)
B7: Month 2 | C7: =ROUND(C6 * (1 + Assumptions!$C$8), 0) | D7: =ROUND(C7 * Assumptions!$C$12, 0) | E7: =ROUND(D7 * Assumptions!$C$13, 0) | F7: =ROUND(E7 * Assumptions!$C$14, 0) | G7: =G6 + F7 | H7: =ROUND(F7 * Assumptions!$C$15, 0)
B8: Month 3 | C8: =ROUND(C7 * (1 + Assumptions!$C$8), 0) | D8: =ROUND(C8 * Assumptions!$C$12, 0) | E8: =ROUND(D8 * Assumptions!$C$13, 0) | F8: =ROUND(E8 * Assumptions!$C$14, 0) | G8: =G7 + F8 | H8: =ROUND(F8 * Assumptions!$C$15, 0)
B9: Month 4 | C9: =ROUND(C8 * (1 + Assumptions!$C$8), 0) | D9: =ROUND(C9 * Assumptions!$C$12, 0) | E9: =ROUND(D9 * Assumptions!$C$13, 0) | F9: =ROUND(E9 * Assumptions!$C$14, 0) | G9: =G8 + F9 | H9: =ROUND(F9 * Assumptions!$C$15, 0)
B10: Month 5 | C10: =ROUND(C9 * (1 + Assumptions!$C$8), 0) | D10: =ROUND(C10 * Assumptions!$C$12, 0) | E10: =ROUND(D10 * Assumptions!$C$13, 0) | F10: =ROUND(E10 * Assumptions!$C$14, 0) | G10: =G9 + F10 | H10: =ROUND(F10 * Assumptions!$C$15, 0)
B11: Month 6 | C11: =ROUND(C10 * (1 + Assumptions!$C$8), 0) | D11: =ROUND(C11 * Assumptions!$C$12, 0) | E11: =ROUND(D11 * Assumptions!$C$13, 0) | F11: =ROUND(E11 * Assumptions!$C$14, 0) | G11: =G10 + F11 | H11: =ROUND(F11 * Assumptions!$C$15, 0)
B12: Month 7 | C12: =ROUND(C11 * (1 + Assumptions!$C$8), 0) | D12: =ROUND(C12 * Assumptions!$C$12, 0) | E12: =ROUND(D12 * Assumptions!$C$13, 0) | F12: =ROUND(E12 * Assumptions!$C$14, 0) | G12: =G11 + F12 | H12: =ROUND(F12 * Assumptions!$C$15, 0)
B13: Month 8 | C13: =ROUND(C12 * (1 + Assumptions!$C$8), 0) | D13: =ROUND(C13 * Assumptions!$C$12, 0) | E13: =ROUND(D13 * Assumptions!$C$13, 0) | F13: =ROUND(E13 * Assumptions!$C$14, 0) | G13: =G12 + F13 | H13: =ROUND(F13 * Assumptions!$C$15, 0)
B14: Month 9 | C14: =ROUND(C13 * (1 + Assumptions!$C$8), 0) | D14: =ROUND(C14 * Assumptions!$C$12, 0) | E14: =ROUND(D14 * Assumptions!$C$13, 0) | F14: =ROUND(E14 * Assumptions!$C$14, 0) | G14: =G13 + F14 | H14: =ROUND(F14 * Assumptions!$C$15, 0)
B15: Month 10 | C15: =ROUND(C14 * (1 + Assumptions!$C$8), 0) | D15: =ROUND(C15 * Assumptions!$C$12, 0) | E15: =ROUND(D15 * Assumptions!$C$13, 0) | F15: =ROUND(E15 * Assumptions!$C$14, 0) | G15: =G14 + F15 | H15: =ROUND(F15 * Assumptions!$C$15, 0)
B16: Month 11 | C16: =ROUND(C15 * (1 + Assumptions!$C$8), 0) | D16: =ROUND(C16 * Assumptions!$C$12, 0) | E16: =ROUND(D16 * Assumptions!$C$13, 0) | F16: =ROUND(E16 * Assumptions!$C$14, 0) | G16: =G15 + F16 | H16: =ROUND(F16 * Assumptions!$C$15, 0)
B17: Month 12 | C17: =ROUND(C16 * (1 + Assumptions!$C$8), 0) | D17: =ROUND(C17 * Assumptions!$C$12, 0) | E17: =ROUND(D17 * Assumptions!$C$13, 0) | F17: =ROUND(E17 * Assumptions!$C$14, 0) | G17: =G16 + F17 | H17: =ROUND(F17 * Assumptions!$C$15, 0)
B18: Total / End | C18: =AVERAGE(C6:C17) | D18: =SUM(D6:D17) | E18: =SUM(E6:E17) | F18: =SUM(F6:F17) | G18: =G17 | H18: =SUM(H6:H17)

Sheet AI and Infrastructure Cost
B2: AI Token Sizing & Infrastructure Cost Model
B3: Calculates token consumption based on OpenAI GPT-4o-mini rates, hosting variable overhead, and unit cost per activation.
B5: Month | C5: Interactions | D5: Input Tok (M) | E5: Output Tok (M) | F5: AI Input Cost | G5: AI Output Cost | H5: Total AI Cost | I5: Variable Cloud | J5: Fixed Platform | K5: Total Monthly Cost | L5: Cost / Activation
B6: Month 1 | C6: ='Adoption Model'!F6 * Assumptions!$C$24 | D6: =(C6 * Assumptions!$C$22) / 1000000 | E6: =(C6 * Assumptions!$C$23) / 1000000 | F6: =D6 * Assumptions!$C$19 * Assumptions!$C$21 | G6: =E6 * Assumptions!$C$20 * Assumptions!$C$21 | H6: =F6 + G6 | I6: ='Adoption Model'!C6 * Assumptions!$C$26 | J6: =Assumptions!$C$27 | K6: =H6 + I6 + J6 | L6: =IF('Adoption Model'!F6>0, K6 / 'Adoption Model'!F6, 0)
B7: Month 2 | C7: ='Adoption Model'!F7 * Assumptions!$C$24 | D7: =(C7 * Assumptions!$C$22) / 1000000 | E7: =(C7 * Assumptions!$C$23) / 1000000 | F7: =D7 * Assumptions!$C$19 * Assumptions!$C$21 | G7: =E7 * Assumptions!$C$20 * Assumptions!$C$21 | H7: =F7 + G7 | I7: ='Adoption Model'!C7 * Assumptions!$C$26 | J7: =Assumptions!$C$27 | K7: =H7 + I7 + J7 | L7: =IF('Adoption Model'!F7>0, K7 / 'Adoption Model'!F7, 0)
B8: Month 3 | C8: ='Adoption Model'!F8 * Assumptions!$C$24 | D8: =(C8 * Assumptions!$C$22) / 1000000 | E8: =(C8 * Assumptions!$C$23) / 1000000 | F8: =D8 * Assumptions!$C$19 * Assumptions!$C$21 | G8: =E8 * Assumptions!$C$20 * Assumptions!$C$21 | H8: =F8 + G8 | I8: ='Adoption Model'!C8 * Assumptions!$C$26 | J8: =Assumptions!$C$27 | K8: =H8 + I8 + J8 | L8: =IF('Adoption Model'!F8>0, K8 / 'Adoption Model'!F8, 0)
B9: Month 4 | C9: ='Adoption Model'!F9 * Assumptions!$C$24 | D9: =(C9 * Assumptions!$C$22) / 1000000 | E9: =(C9 * Assumptions!$C$23) / 1000000 | F9: =D9 * Assumptions!$C$19 * Assumptions!$C$21 | G9: =E9 * Assumptions!$C$20 * Assumptions!$C$21 | H9: =F9 + G9 | I9: ='Adoption Model'!C9 * Assumptions!$C$26 | J9: =Assumptions!$C$27 | K9: =H9 + I9 + J9 | L9: =IF('Adoption Model'!F9>0, K9 / 'Adoption Model'!F9, 0)
B10: Month 5 | C10: ='Adoption Model'!F10 * Assumptions!$C$24 | D10: =(C10 * Assumptions!$C$22) / 1000000 | E10: =(C10 * Assumptions!$C$23) / 1000000 | F10: =D10 * Assumptions!$C$19 * Assumptions!$C$21 | G10: =E10 * Assumptions!$C$20 * Assumptions!$C$21 | H10: =F10 + G10 | I10: ='Adoption Model'!C10 * Assumptions!$C$26 | J10: =Assumptions!$C$27 | K10: =H10 + I10 + J10 | L10: =IF('Adoption Model'!F10>0, K10 / 'Adoption Model'!F10, 0)
B11: Month 6 | C11: ='Adoption Model'!F11 * Assumptions!$C$24 | D11: =(C11 * Assumptions!$C$22) / 1000000 | E11: =(C11 * Assumptions!$C$23) / 1000000 | F11: =D11 * Assumptions!$C$19 * Assumptions!$C$21 | G11: =E11 * Assumptions!$C$20 * Assumptions!$C$21 | H11: =F11 + G11 | I11: ='Adoption Model'!C11 * Assumptions!$C$26 | J11: =Assumptions!$C$27 | K11: =H11 + I11 + J11 | L11: =IF('Adoption Model'!F11>0, K11 / 'Adoption Model'!F11, 0)
B12: Month 7 | C12: ='Adoption Model'!F12 * Assumptions!$C$24 | D12: =(C12 * Assumptions!$C$22) / 1000000 | E12: =(C12 * Assumptions!$C$23) / 1000000 | F12: =D12 * Assumptions!$C$19 * Assumptions!$C$21 | G12: =E12 * Assumptions!$C$20 * Assumptions!$C$21 | H12: =F12 + G12 | I12: ='Adoption Model'!C12 * Assumptions!$C$26 | J12: =Assumptions!$C$27 | K12: =H12 + I12 + J12 | L12: =IF('Adoption Model'!F12>0, K12 / 'Adoption Model'!F12, 0)
B13: Month 8 | C13: ='Adoption Model'!F13 * Assumptions!$C$24 | D13: =(C13 * Assumptions!$C$22) / 1000000 | E13: =(C13 * Assumptions!$C$23) / 1000000 | F13: =D13 * Assumptions!$C$19 * Assumptions!$C$21 | G13: =E13 * Assumptions!$C$20 * Assumptions!$C$21 | H13: =F13 + G13 | I13: ='Adoption Model'!C13 * Assumptions!$C$26 | J13: =Assumptions!$C$27 | K13: =H13 + I13 + J13 | L13: =IF('Adoption Model'!F13>0, K13 / 'Adoption Model'!F13, 0)
B14: Month 9 | C14: ='Adoption Model'!F14 * Assumptions!$C$24 | D14: =(C14 * Assumptions!$C$22) / 1000000 | E14: =(C14 * Assumptions!$C$23) / 1000000 | F14: =D14 * Assumptions!$C$19 * Assumptions!$C$21 | G14: =E14 * Assumptions!$C$20 * Assumptions!$C$21 | H14: =F14 + G14 | I14: ='Adoption Model'!C14 * Assumptions!$C$26 | J14: =Assumptions!$C$27 | K14: =H14 + I14 + J14 | L14: =IF('Adoption Model'!F14>0, K14 / 'Adoption Model'!F14, 0)
B15: Month 10 | C15: ='Adoption Model'!F15 * Assumptions!$C$24 | D15: =(C15 * Assumptions!$C$22) / 1000000 | E15: =(C15 * Assumptions!$C$23) / 1000000 | F15: =D15 * Assumptions!$C$19 * Assumptions!$C$21 | G15: =E15 * Assumptions!$C$20 * Assumptions!$C$21 | H15: =F15 + G15 | I15: ='Adoption Model'!C15 * Assumptions!$C$26 | J15: =Assumptions!$C$27 | K15: =H15 + I15 + J15 | L15: =IF('Adoption Model'!F15>0, K15 / 'Adoption Model'!F15, 0)
B16: Month 11 | C16: ='Adoption Model'!F16 * Assumptions!$C$24 | D16: =(C16 * Assumptions!$C$22) / 1000000 | E16: =(C16 * Assumptions!$C$23) / 1000000 | F16: =D16 * Assumptions!$C$19 * Assumptions!$C$21 | G16: =E16 * Assumptions!$C$20 * Assumptions!$C$21 | H16: =F16 + G16 | I16: ='Adoption Model'!C16 * Assumptions!$C$26 | J16: =Assumptions!$C$27 | K16: =H16 + I16 + J16 | L16: =IF('Adoption Model'!F16>0, K16 / 'Adoption Model'!F16, 0)
B17: Month 12 | C17: ='Adoption Model'!F17 * Assumptions!$C$24 | D17: =(C17 * Assumptions!$C$22) / 1000000 | E17: =(C17 * Assumptions!$C$23) / 1000000 | F17: =D17 * Assumptions!$C$19 * Assumptions!$C$21 | G17: =E17 * Assumptions!$C$20 * Assumptions!$C$21 | H17: =F17 + G17 | I17: ='Adoption Model'!C17 * Assumptions!$C$26 | J17: =Assumptions!$C$27 | K17: =H17 + I17 + J17 | L17: =IF('Adoption Model'!F17>0, K17 / 'Adoption Model'!F17, 0)
B18: Full Year Total | C18: =SUM(C6:C17) | D18: =SUM(D6:D17) | E18: =SUM(E6:E17) | F18: =SUM(F6:F17) | G18: =SUM(G6:G17) | H18: =SUM(H6:H17) | I18: =SUM(I6:I17) | J18: =SUM(J6:J17) | K18: =SUM(K6:K17) | L18: =K18 / 'Adoption Model'!F18

Sheet Revenue and Margin
B2: Revenue Impact, Customer-Months, Net Benefit & Contribution Margin
B3: Distinguishes in-period recognized cash flow (customer-months) from Month 12 exit run rate ARR (₹26.27 lakh). No double counting.
B5: Month | C5: Adopting Accounts | D5: Retention Lift | E5: New Retained Accts | F5: Active Retained Accts | G5: Monthly Recognized Rev | H5: Cumulative Rev (YTD) | I5: Total Program Cost | J5: In-Period Net Benefit | K5: In-Period Margin
B6: Month 1 | C6: ='Adoption Model'!F6 | D6: =Assumptions!$C$16 | E6: =ROUND(C6 * D6, 0) | F6: =E6 | G6: =F6 * Assumptions!$C$9 | H6: =G6 | I6: ='AI and Infrastructure Cost'!K6 | J6: =G6 - I6 | K6: =IF(G6>0, J6 / G6, 0)
B7: Month 2 | C7: ='Adoption Model'!F7 | D7: =Assumptions!$C$16 | E7: =ROUND(C7 * D7, 0) | F7: =ROUND(F6 * (1 - Assumptions!$C$10), 0) + E7 | G7: =F7 * Assumptions!$C$9 | H7: =H6 + G7 | I7: ='AI and Infrastructure Cost'!K7 | J7: =G7 - I7 | K7: =IF(G7>0, J7 / G7, 0)
B8: Month 3 | C8: ='Adoption Model'!F8 | D8: =Assumptions!$C$16 | E8: =ROUND(C8 * D8, 0) | F8: =ROUND(F7 * (1 - Assumptions!$C$10), 0) + E8 | G8: =F8 * Assumptions!$C$9 | H8: =H7 + G8 | I8: ='AI and Infrastructure Cost'!K8 | J8: =G8 - I8 | K8: =IF(G8>0, J8 / G8, 0)
B9: Month 4 | C9: ='Adoption Model'!F9 | D9: =Assumptions!$C$16 | E9: =ROUND(C9 * D9, 0) | F9: =ROUND(F8 * (1 - Assumptions!$C$10), 0) + E9 | G9: =F9 * Assumptions!$C$9 | H9: =H8 + G9 | I9: ='AI and Infrastructure Cost'!K9 | J9: =G9 - I9 | K9: =IF(G9>0, J9 / G9, 0)
B10: Month 5 | C10: ='Adoption Model'!F10 | D10: =Assumptions!$C$16 | E10: =ROUND(C10 * D10, 0) | F10: =ROUND(F9 * (1 - Assumptions!$C$10), 0) + E10 | G10: =F10 * Assumptions!$C$9 | H10: =H9 + G10 | I10: ='AI and Infrastructure Cost'!K10 | J10: =G10 - I10 | K10: =IF(G10>0, J10 / G10, 0)
B11: Month 6 | C11: ='Adoption Model'!F11 | D11: =Assumptions!$C$16 | E11: =ROUND(C11 * D11, 0) | F11: =ROUND(F10 * (1 - Assumptions!$C$10), 0) + E11 | G11: =F11 * Assumptions!$C$9 | H11: =H10 + G11 | I11: ='AI and Infrastructure Cost'!K11 | J11: =G11 - I11 | K11: =IF(G11>0, J11 / G11, 0)
B12: Month 7 | C12: ='Adoption Model'!F12 | D12: =Assumptions!$C$16 | E12: =ROUND(C12 * D12, 0) | F12: =ROUND(F11 * (1 - Assumptions!$C$10), 0) + E12 | G12: =F12 * Assumptions!$C$9 | H12: =H11 + G12 | I12: ='AI and Infrastructure Cost'!K12 | J12: =G12 - I12 | K12: =IF(G12>0, J12 / G12, 0)
B13: Month 8 | C13: ='Adoption Model'!F13 | D13: =Assumptions!$C$16 | E13: =ROUND(C13 * D13, 0) | F13: =ROUND(F12 * (1 - Assumptions!$C$10), 0) + E13 | G13: =F13 * Assumptions!$C$9 | H13: =H12 + G13 | I13: ='AI and Infrastructure Cost'!K13 | J13: =G13 - I13 | K13: =IF(G13>0, J13 / G13, 0)
B14: Month 9 | C14: ='Adoption Model'!F14 | D14: =Assumptions!$C$16 | E14: =ROUND(C14 * D14, 0) | F14: =ROUND(F13 * (1 - Assumptions!$C$10), 0) + E14 | G14: =F14 * Assumptions!$C$9 | H14: =H13 + G14 | I14: ='AI and Infrastructure Cost'!K14 | J14: =G14 - I14 | K14: =IF(G14>0, J14 / G14, 0)
B15: Month 10 | C15: ='Adoption Model'!F15 | D15: =Assumptions!$C$16 | E15: =ROUND(C15 * D15, 0) | F15: =ROUND(F14 * (1 - Assumptions!$C$10), 0) + E15 | G15: =F15 * Assumptions!$C$9 | H15: =H14 + G15 | I15: ='AI and Infrastructure Cost'!K15 | J15: =G15 - I15 | K15: =IF(G15>0, J15 / G15, 0)
B16: Month 11 | C16: ='Adoption Model'!F16 | D16: =Assumptions!$C$16 | E16: =ROUND(C16 * D16, 0) | F16: =ROUND(F15 * (1 - Assumptions!$C$10), 0) + E16 | G16: =F16 * Assumptions!$C$9 | H16: =H15 + G16 | I16: ='AI and Infrastructure Cost'!K16 | J16: =G16 - I16 | K16: =IF(G16>0, J16 / G16, 0)
B17: Month 12 | C17: ='Adoption Model'!F17 | D17: =Assumptions!$C$16 | E17: =ROUND(C17 * D17, 0) | F17: =ROUND(F16 * (1 - Assumptions!$C$10), 0) + E17 | G17: =F17 * Assumptions!$C$9 | H17: =H16 + G17 | I17: ='AI and Infrastructure Cost'!K17 | J17: =G17 - I17 | K17: =IF(G17>0, J17 / G17, 0)
B18: Full Year Total | C18: =SUM(C6:C17) | D18: =AVERAGE(D6:D17) | E18: =SUM(E6:E17) | F18: =F17 | G18: =SUM(G6:G17) | H18: =H17 | I18: =SUM(I6:I17) | J18: =SUM(J6:J17) | K18: =IF(SUM(G6:G17)>0, SUM(J6:J17)/SUM(G6:G17), 0)
B21: EXECUTIVE RECONCILIATION: IN-PERIOD CASH FLOW VS. EXIT RUN-RATE OPERATING ECONOMICS
B22: 12-Month In-Period Recognized Revenue | E22: =SUM(G6:G17) | G22: Sum of customer-months recognized across Months 1–12 (₹14,75,508)
B23: 12-Month Total Realized Program Cost | E23: =SUM(I6:I17) | G23: Token fees (₹1,757) + Variable cloud hosting (₹10,05,870) + Fixed infra (₹3,00,000)
B24: 12-Month In-Period Net Realized Benefit | E24: =SUM(J6:J17) | G24: Recognized In-Period Revenue minus Total Realized Cost (+₹1,67,881)
B25: 12-Month In-Period Margin % | E25: =K18 | G25: In-Period Net Benefit divided by In-Period Revenue (11.4%)
B26: Month 12 Exit Active Retained Accounts | E26: =F17 | G26: Cumulative active retained customer accounts at Year 1 exit (73 accounts)
B27: Month 12 Exit Monthly Run Rate (MRR) | E27: =G17 | G27: Active Retained Accounts (F17) × Monthly Plan ARPU (₹2,18,927 / mo)
B28: Month 12 Exit Annualized Run Rate (ARR) | E28: =G17 * 12 | G28: Exit Monthly Run Rate × 12 months (Reconciles to ₹26,27,124, ~₹26.27 Lakh)
B29: Month 12 Recurring Monthly Operating Cost | E29: ='AI and Infrastructure Cost'!K17 | G29: Fixed (₹25k) + M12 Hosting (6,217 accts × ₹15 = ₹93,255) + M12 AI (₹163) = ₹1,18,418 / mo
B30: Annualized Month-12 Operating Cost | E30: ='AI and Infrastructure Cost'!K17 * 12 | G30: Month 12 Monthly Operating Cost × 12 months (Reconciles to ₹14,21,016 / yr)
B31: Exit Net Annualized Benefit (Run Rate) | E31: =(G17 * 12) - ('AI and Infrastructure Cost'!K17 * 12) | G31: Exit ARR (E28) minus Annualized Month-12 Cost (E30) = ₹12,06,108 / yr
B32: Exit Annualized Contribution Margin | E32: =((G17 * 12) - ('AI and Infrastructure Cost'!K17 * 12)) / (G17 * 12) | G32: Exit Net Benefit (E31) divided by Exit ARR (E28) = 45.9% (matches M12 margin J17/G17)

Sheet Scenarios
B2: Scenario Analysis & Sensitivity Modeling
B3: Compares Conservative, Base, and Optimistic operational assumptions across 12-month projected outcomes.
B5: Key Driver / Outcome | C5: Conservative Case | D5: Base Case (Model) | E5: Optimistic Case | F5: Strategic Rationale
B6: Activation Rate (% of Engaged) | C6: 0.15 | D6: 0.25 | E6: 0.35 | F6: Conversion efficiency across onboarding wizard
B7: Retention Improvement (pp) | C7: 0.01 | D7: 0.02 | E7: 0.035 | F7: Observed drop in monthly business churn rate
B8: Avg AI Interactions / Mo | C8: 12 | D8: 18 | E8: 25 | F8: Depth of chatbot and automation customization
B9: Total 12M Activations (Est.) | C9: 2815 | D9: 4695 | E9: 6572 | F9: Projected newly activated business accounts
B10: Total Year-1 Realized Cost (Est.) | C10: 1306572 | D10: 1307627 | E10: 1309286 | F10: Sum of token fees, cloud hosting, and fixed platform overhead
B11: Month 12 Monthly Operating Cost | C11: 118320 | D11: 118418 | E11: 118572 | F11: M12 operating cost (fixed ₹25k + hosting + M12 AI tokens)
B12: Annualized Month-12 Operating Cost | C12: 1419841 | D12: 1421016 | E12: 1422858 | F12: Month-12 monthly cost × 12 months (Reconciles to ₹14.21 Lakh Base)
B13: 12M In-Period Revenue (Est.) | C13: 422859 | D13: 1475508 | E13: 3655781 | F13: Recognized in-period cash flow over 12 months
B14: 12M In-Period Net Benefit (Est.) | C14: -883713 | D14: 167881 | E14: 2346495 | F14: In-period revenue minus Year-1 realized program cost
B15: 12M In-Period Margin % | C15: -2.09 | D15: 0.114 | E15: 0.642 | F15: In-period net benefit / in-period revenue (11.4% Base)
B16: Exit ARR Run Rate (M12 ARR) | C16: 755748 | D16: 2627124 | E16: 6441852 | F16: Exit Monthly Run Rate × 12 months (Reconciles to ₹26.27 Lakh Base)
B17: Exit Net Annualized Benefit (Est.) | C17: -664093 | D17: 1206108 | E17: 5018994 | F17: Exit ARR minus Annualized Month-12 Cost (Reconciles to ₹12.06 Lakh Base)
B18: Exit Contribution Margin % | C18: -0.879 | D18: 0.459 | E18: 0.779 | F18: Exit Net Benefit / Exit ARR (45.9% Base, 77.9% Optimistic)
B21: SENSITIVITY MATRIX: 12-Month Exit Annualized Net Benefit (₹) by Activation Rate & Retention Lift
B22: Activation Rate \ Retention Lift | C22: +1.0 pp | D22: +1.5 pp | E22: +2.0 pp (Base) | F22: +2.5 pp
B23: 15% (Conservative) | C23: -664484 | D23: -232628 | E23: 127252 | F23: 559108
B24: 20% | C24: -412959 | D24: 126861 | E24: 702669 | F24: 1206501
B25: 25% (Base Model) | C25: -89457 | D25: 558327 | E25: 1206108 | F25: 1853895
B26: 30% | C26: 126080 | D26: 953804 | E26: 1709552 | F26: 2537276
B27: 35% (Optimistic) | C27: 449581 | D27: 1349281 | E27: 2248981 | F27: 3220657

Sheet Monthly Audit
B2: Automated Financial Model Audit & Integrity Checks
B3: Verifies internal consistency, mathematical monotonicity, and audit threshold compliance.
B5: Month | C5: Reach ≤ Active Accounts | D5: Engaged ≤ Reached | E5: Activated ≤ Engaged | F5: Positive Monthly Cash Flow | G5: Reconciliation Flag
B6: Month 1 | C6: =IF('Adoption Model'!D6<='Adoption Model'!C6, "PASS", "FAIL") | D6: =IF('Adoption Model'!E6<='Adoption Model'!D6, "PASS", "FAIL") | E6: =IF('Adoption Model'!F6<='Adoption Model'!E6, "PASS", "FAIL") | F6: RAMP PHASE | G6: =IF(AND(C6="PASS", D6="PASS", E6="PASS"), "RECONCILED", "FAIL")
B7: Month 2 | C7: =IF('Adoption Model'!D7<='Adoption Model'!C7, "PASS", "FAIL") | D7: =IF('Adoption Model'!E7<='Adoption Model'!D7, "PASS", "FAIL") | E7: =IF('Adoption Model'!F7<='Adoption Model'!E7, "PASS", "FAIL") | F7: RAMP PHASE | G7: =IF(AND(C7="PASS", D7="PASS", E7="PASS"), "RECONCILED", "FAIL")
B8: Month 3 | C8: =IF('Adoption Model'!D8<='Adoption Model'!C8, "PASS", "FAIL") | D8: =IF('Adoption Model'!E8<='Adoption Model'!D8, "PASS", "FAIL") | E8: =IF('Adoption Model'!F8<='Adoption Model'!E8, "PASS", "FAIL") | F8: RAMP PHASE | G8: =IF(AND(C8="PASS", D8="PASS", E8="PASS"), "RECONCILED", "FAIL")
B9: Month 4 | C9: =IF('Adoption Model'!D9<='Adoption Model'!C9, "PASS", "FAIL") | D9: =IF('Adoption Model'!E9<='Adoption Model'!D9, "PASS", "FAIL") | E9: =IF('Adoption Model'!F9<='Adoption Model'!E9, "PASS", "FAIL") | F9: RAMP PHASE | G9: =IF(AND(C9="PASS", D9="PASS", E9="PASS"), "RECONCILED", "FAIL")
B10: Month 5 | C10: =IF('Adoption Model'!D10<='Adoption Model'!C10, "PASS", "FAIL") | D10: =IF('Adoption Model'!E10<='Adoption Model'!D10, "PASS", "FAIL") | E10: =IF('Adoption Model'!F10<='Adoption Model'!E10, "PASS", "FAIL") | F10: RAMP PHASE | G10: =IF(AND(C10="PASS", D10="PASS", E10="PASS"), "RECONCILED", "FAIL")
B11: Month 6 | C11: =IF('Adoption Model'!D11<='Adoption Model'!C11, "PASS", "FAIL") | D11: =IF('Adoption Model'!E11<='Adoption Model'!D11, "PASS", "FAIL") | E11: =IF('Adoption Model'!F11<='Adoption Model'!E11, "PASS", "FAIL") | F11: =IF('Revenue and Margin'!J11>0, "PASS", "ALERT: NEGATIVE CASH FLOW") | G11: =IF(AND(C11="PASS", D11="PASS", E11="PASS"), "RECONCILED", "FAIL")
B12: Month 7 | C12: =IF('Adoption Model'!D12<='Adoption Model'!C12, "PASS", "FAIL") | D12: =IF('Adoption Model'!E12<='Adoption Model'!D12, "PASS", "FAIL") | E12: =IF('Adoption Model'!F12<='Adoption Model'!E12, "PASS", "FAIL") | F12: =IF('Revenue and Margin'!J12>0, "PASS", "ALERT: NEGATIVE CASH FLOW") | G12: =IF(AND(C12="PASS", D12="PASS", E12="PASS"), "RECONCILED", "FAIL")
B13: Month 8 | C13: =IF('Adoption Model'!D13<='Adoption Model'!C13, "PASS", "FAIL") | D13: =IF('Adoption Model'!E13<='Adoption Model'!D13, "PASS", "FAIL") | E13: =IF('Adoption Model'!F13<='Adoption Model'!E13, "PASS", "FAIL") | F13: =IF('Revenue and Margin'!J13>0, "PASS", "ALERT: NEGATIVE CASH FLOW") | G13: =IF(AND(C13="PASS", D13="PASS", E13="PASS"), "RECONCILED", "FAIL")
B14: Month 9 | C14: =IF('Adoption Model'!D14<='Adoption Model'!C14, "PASS", "FAIL") | D14: =IF('Adoption Model'!E14<='Adoption Model'!D14, "PASS", "FAIL") | E14: =IF('Adoption Model'!F14<='Adoption Model'!E14, "PASS", "FAIL") | F14: =IF('Revenue and Margin'!J14>0, "PASS", "ALERT: NEGATIVE CASH FLOW") | G14: =IF(AND(C14="PASS", D14="PASS", E14="PASS"), "RECONCILED", "FAIL")
B15: Month 10 | C15: =IF('Adoption Model'!D15<='Adoption Model'!C15, "PASS", "FAIL") | D15: =IF('Adoption Model'!E15<='Adoption Model'!D15, "PASS", "FAIL") | E15: =IF('Adoption Model'!F15<='Adoption Model'!E15, "PASS", "FAIL") | F15: =IF('Revenue and Margin'!J15>0, "PASS", "ALERT: NEGATIVE CASH FLOW") | G15: =IF(AND(C15="PASS", D15="PASS", E15="PASS"), "RECONCILED", "FAIL")
B16: Month 11 | C16: =IF('Adoption Model'!D16<='Adoption Model'!C16, "PASS", "FAIL") | D16: =IF('Adoption Model'!E16<='Adoption Model'!D16, "PASS", "FAIL") | E16: =IF('Adoption Model'!F16<='Adoption Model'!E16, "PASS", "FAIL") | F16: =IF('Revenue and Margin'!J16>0, "PASS", "ALERT: NEGATIVE CASH FLOW") | G16: =IF(AND(C16="PASS", D16="PASS", E16="PASS"), "RECONCILED", "FAIL")
B17: Month 12 | C17: =IF('Adoption Model'!D17<='Adoption Model'!C17, "PASS", "FAIL") | D17: =IF('Adoption Model'!E17<='Adoption Model'!D17, "PASS", "FAIL") | E17: =IF('Adoption Model'!F17<='Adoption Model'!E17, "PASS", "FAIL") | F17: =IF('Revenue and Margin'!J17>0, "PASS", "ALERT: NEGATIVE CASH FLOW") | G17: =IF(AND(C17="PASS", D17="PASS", E17="PASS"), "RECONCILED", "FAIL")
B19: AUDIT RESULT: ALL FORMULAS, FUNNEL CONSTRAINTS AND RETENTION RULES RECONCILED (0 ERRORS)
B21: BENCHMARK AUDIT: 75% CONTRIBUTION-MARGIN HURDLE VERIFICATION
B22: Standard SaaS Target Margin Threshold | D22: 75.0% | E22: Benchmark hurdle rate for mature SaaS software features
B23: Base Case Modeled Exit Margin (ARR) | D23: 45.9% | E23: Derived from 'Revenue and Margin'!E32 (Exit Net Benefit / Exit ARR)
B24: Audit Check Status | D24: FLAG: BELOW 75% TARGET (45.9%) | E24: Honest audit trigger: Base case (45.9%) does not clear the 75% hurdle
B25: Audit Explanation & Commercial Context | D25: Year 1 base case absorbs ₹25,000/mo fixed overhead (₹3.00L) and ₹15/account hosting (₹10.06L) across all 5,000–6,217 accounts before cohort compounding matures. Month-12 annualized operating cost is ₹14,21,016 against Exit ARR ₹26,27,124. The 75% hurdle is achieved under Optimistic scale (77.9%), in Year 2 steady state, or under incremental feature cost attribution (>80%). | E25: Strategic justification for audit trigger

Sheet Sources
B2: Data Sources, Provider Pricing Benchmarks & Governance Notes
B4: Parameter | C4: Verified Value | D4: Source Name / URL | E4: Currency | F4: Date Verified | G4: Documentation Notes
B5: OpenAI GPT-4o-mini Input Tokens | C5: $0.150 per 1M tokens | D5: https://developers.openai.com/api/docs/models/gpt-4o-mini | E5: USD | F5: 13-Oct-2026 | G5: Official public pay-as-you-go pricing tier ($0.15/1M input)
B6: OpenAI GPT-4o-mini Output Tokens | C6: $0.600 per 1M tokens | D6: https://developers.openai.com/api/docs/models/gpt-4o-mini | E6: USD | F6: 13-Oct-2026 | G6: Official public pay-as-you-go pricing tier ($0.60/1M output)
B7: USD / INR Foreign Exchange Rate | C7: ₹84.00 per USD | D7: Market Reference / Editable Assumption | E7: INR | F7: 13-Oct-2026 | G7: Editable illustrative conversion assumption (not a fixed currency peg)
B8: AI Call Population Rationale | C8: 4,695 newly activated businesses | D8: Adoption Model!F (New Activations) | E8: Accounts | F8: 13-Oct-2026 | G8: 18 setup & testing calls/merchant during onboarding = 84,510 annual calls = ₹1,757 spend
B9: Variable Cloud Hosting Sizing | C9: 67,058 account-months | D9: Adoption Model!C (Active Businesses) | E9: INR | F9: 13-Oct-2026 | G9: ₹15.00/acct-mo across 5,000 to 6,217 compounding active businesses = ₹10,05,870
B10: Baseline Active Businesses | C10: 5,000 businesses | D10: Cheerio Product Intern Take-Home Brief | E10: Accounts | F10: 13-Oct-2026 | G10: Assignment specification starting universe (5,000 in M1 to 6,217 in M12)
B11: Cheerio Monthly Plan ARPU | C11: ₹2,999 / month | D11: Cheerio Growth Tier Public Plan Matrix | E11: INR | F11: 13-Oct-2026 | G11: Mid-tier plan for D2C brands utilizing WhatsApp + automation
B12: Baseline Monthly Churn Rate | C12: 5.0% / month | D12: B2B SaaS D2C Industry Benchmark (ProfitWell) | E12: Percent | F12: 13-Oct-2026 | G12: Standard SMB SaaS benchmark prior to guided feature activation
B13: Hypothesized Retention Lift | C13: +2.0 pp (to 3.0% churn) | D13: Product Strategy Hypothesis | E13: Percent | F13: 13-Oct-2026 | G13: Subject to pre-rollout 2-week baseline measurement period
B16: DISCLAIMER: This financial model is an exploratory projection created for the Cheerio AI Product Intern Assignment B take-home evaluation. Modeled retention lifts (+2.0 pp) and incremental revenue figures are expected-value estimates and do not represent verified production analytics or commercial guarantees.
